demo_example_package/__init__.py
demo_example_package-0.1.9.dist-info/METADATA
demo_example_package-0.1.9.dist-info/WHEEL
demo_example_package-0.1.9.dist-info/licenses/LICENSE
demo_example_package-0.1.9.dist-info/RECORD
