Metadata-Version: 2.4
Name: demo-example-package
Version: 0.1.9
Summary: A modern Python package with complete CI/CD setup
Project-URL: Homepage, https://github.com/serafinovsky/demo-example-package
Project-URL: Documentation, https://github.com/serafinovsky/demo-example-package#readme
Project-URL: Repository, https://github.com/serafinovsky/demo-example-package
Project-URL: Issues, https://github.com/serafinovsky/demo-example-package/issues
Author-email: Mark Serafinovsky <m.serafinovsky@gmail.com>
License: MIT
License-File: LICENSE
Keywords: package,python
Classifier: Development Status :: 5 - Production/Stable
Classifier: Intended Audience :: Developers
Classifier: License :: OSI Approved :: MIT License
Classifier: Operating System :: OS Independent
Classifier: Programming Language :: Python :: 3
Classifier: Programming Language :: Python :: 3.11
Classifier: Programming Language :: Python :: 3.12
Classifier: Programming Language :: Python :: 3.13
Classifier: Topic :: Software Development :: Libraries :: Python Modules
Classifier: Typing :: Typed
Requires-Python: >=3.11
